statikk/__init__.py
statikk/conditions.py
statikk/engine.py
statikk/expressions.py
statikk/fields.py
statikk/models.py
statikk/typing.py
statikk-0.1.28.dist-info/licenses/LICENSE.txt
statikk-0.1.28.dist-info/METADATA
statikk-0.1.28.dist-info/WHEEL
statikk-0.1.28.dist-info/top_level.txt
statikk-0.1.28.dist-info/RECORD
