Metadata-Version: 2.4
Name: statikk
Version: 0.1.28
Summary: statikk is a single table application (STA) library for DynamoDb.
Home-page: https://github.com/terinia/statikk
Author: Balint Biro
Author-email: rockbag123@gmail.com
License: MIT
Project-URL: Documentation, https://terinia.com/
Platform: any
Classifier: Development Status :: 4 - Beta
Classifier: Programming Language :: Python
Requires-Python: >=3.8
License-File: LICENSE.txt
Requires-Dist: importlib-metadata; python_version < "3.8"
Requires-Dist: pydantic<3.0,>=2.7.4
Requires-Dist: boto3<2.0,>=1.28.43
Requires-Dist: aws-xray-sdk<3.0,>=2.14.0
Provides-Extra: testing
Requires-Dist: setuptools; extra == "testing"
Requires-Dist: pytest; extra == "testing"
Requires-Dist: pytest-cov; extra == "testing"
Requires-Dist: moto[dynamodb]==4.2.14; extra == "testing"
Dynamic: license-file
